MANIFEST.in
README.rst
pyproject.toml
setup.cfg
setup.py
src/ngits_tickets.egg-info/PKG-INFO
src/ngits_tickets.egg-info/SOURCES.txt
src/ngits_tickets.egg-info/dependency_links.txt
src/ngits_tickets.egg-info/requires.txt
src/ngits_tickets.egg-info/top_level.txt
src/tickets/__init__.py
src/tickets/admin.py
src/tickets/apps.py
src/tickets/consts.py
src/tickets/models.py
src/tickets/serializers.py
src/tickets/urls.py
src/tickets/views.py
src/tickets/migrations/0001_initial.py
src/tickets/migrations/0002_ticket_type.py
src/tickets/migrations/0003_alter_ticket_type.py
src/tickets/migrations/__init__.py